{
    "parameters": {
        "source_domains": [
            "photo"
        ],
        "target_domains": [
            "sketch"
        ],
        "model_path": "/scratch/gautschi/apiasecz/models/concept_drift_models/PACSCNN_1_photo_seed_3.pth",
        "model_architecture": "PACSCNN_1",
        "seed": 3,
        "n_rounds": 200,
        "learning_rate": 0.005,
        "batch_size": 128,
        "policy_id": 2,
        "setting_id": 5,
        "pi_bar": 0.25,
        "V": 65,
        "K_p": 1.0,
        "K_d": 1.0
    },
    "schedule_params": {
        "schedule_type": "domain_change_burst_2",
        "burst_interval": 50,
        "burst_duration": 5,
        "base_rate": 0.0,
        "burst_rate": 0.2,
        "initial_delay": 50,
        "target_domains": [
            "cartoon",
            "sketch",
            "photo"
        ]
    },
    "results": [
        {
            "t": 0,
            "accuracy": 0.7248263955116272,
            "loss": 0.9957723048600283,
            "decision": 1,
            "drift_rate": 0.0,
            "target_domain": "cartoon"
        },
        {
            "t": 1,
            "accuracy": 0.6762152910232544,
            "loss": 0.9688919078220021,
            "decision": 0,
            "drift_rate": 0.0,
            "target_domain": "cartoon"
        },
        {
            "t": 2,
            "accuracy": 0.6762152910232544,
            "loss": 0.9594280015338551,
            "decision": 0,
            "drift_rate": 0.0,
            "target_domain": "cartoon"
        },
        {
            "t": 3,
            "accuracy": 0.6762152910232544,
            "loss": 0.9638427279212258,
            "decision": 0,
            "drift_rate": 0.0,
            "target_domain": "cartoon"
        },
        {
            "t": 4,
            "accuracy": 0.6762152910232544,
            "loss": 0.9249863434921611,
            "decision": 1,
            "drift_rate": 0.0,
            "target_domain": "cartoon"
        },
        {
            "t": 5,
            "accuracy": 0.6345486243565878,
            "loss": 0.9335688731887124,
            "decision": 0,
            "drift_rate": 0.0,
            "target_domain": "cartoon"
        },
        {
            "t": 6,
            "accuracy": 0.6345486243565878,
            "loss": 0.9359339584003795,
            "decision": 0,
            "drift_rate": 0.0,
            "target_domain": "cartoon"
        },
        {
            "t": 7,
            "accuracy": 0.6345486243565878,
            "loss": 0.9340910911560059,
            "decision": 0,
            "drift_rate": 0.0,
            "target_domain": "cartoon"
        },
        {
            "t": 8,
            "accuracy": 0.6345486243565878,
            "loss": 0.8900561657818882,
            "decision": 1,
            "drift_rate": 0.0,
            "target_domain": "cartoon"
        },
        {
            "t": 9,
            "accuracy": 0.655381957689921,
            "loss": 1.0142015598037026,
            "decision": 0,
            "drift_rate": 0.0,
            "target_domain": "cartoon"
        },
        {
            "t": 10,
            "accuracy": 0.655381957689921,
            "loss": 1.0220672704956748,
            "decision": 0,
            "drift_rate": 0.0,
            "target_domain": "cartoon"
        },
        {
            "t": 11,
            "accuracy": 0.655381957689921,
            "loss": 1.019958344372836,
            "decision": 0,
            "drift_rate": 0.0,
            "target_domain": "cartoon"
        },
        {
            "t": 12,
            "accuracy": 0.655381957689921,
            "loss": 0.8836462064222856,
            "decision": 1,
            "drift_rate": 0.0,
            "target_domain": "cartoon"
        },
        {
            "t": 13,
            "accuracy": 0.6206597288449606,
            "loss": 0.9891808683221991,
            "decision": 0,
            "drift_rate": 0.0,
            "target_domain": "cartoon"
        },
        {
            "t": 14,
            "accuracy": 0.6206597288449606,
            "loss": 0.9854905388572,
            "decision": 0,
            "drift_rate": 0.0,
            "target_domain": "cartoon"
        },
        {
            "t": 15,
            "accuracy": 0.6206597288449606,
            "loss": 0.9906994050199335,
            "decision": 0,
            "drift_rate": 0.0,
            "target_domain": "cartoon"
        },
        {
            "t": 16,
            "accuracy": 0.6206597288449606,
            "loss": 0.875527335838838,
            "decision": 1,
            "drift_rate": 0.0,
            "target_domain": "cartoon"
        },
        {
            "t": 17,
            "accuracy": 0.6449652910232544,
            "loss": 0.9419796900315718,
            "decision": 0,
            "drift_rate": 0.0,
            "target_domain": "cartoon"
        },
        {
            "t": 18,
            "accuracy": 0.6449652910232544,
            "loss": 0.9371883869171143,
            "decision": 0,
            "drift_rate": 0.0,
            "target_domain": "cartoon"
        },
        {
            "t": 19,
            "accuracy": 0.6449652910232544,
            "loss": 0.9301215193488381,
            "decision": 0,
            "drift_rate": 0.0,
            "target_domain": "cartoon"
        },
        {
            "t": 20,
            "accuracy": 0.6449652910232544,
            "loss": 0.8675081431865692,
            "decision": 1,
            "drift_rate": 0.0,
            "target_domain": "cartoon"
        },
        {
            "t": 21,
            "accuracy": 0.5347222288449606,
            "loss": 1.2289298339323564,
            "decision": 0,
            "drift_rate": 0.0,
            "target_domain": "cartoon"
        },
        {
            "t": 22,
            "accuracy": 0.5347222288449606,
            "loss": 1.2293591824444858,
            "decision": 0,
            "drift_rate": 0.0,
            "target_domain": "cartoon"
        },
        {
            "t": 23,
            "accuracy": 0.5347222288449606,
            "loss": 1.2363965132019736,
            "decision": 0,
            "drift_rate": 0.0,
            "target_domain": "cartoon"
        },
        {
            "t": 24,
            "accuracy": 0.5347222288449606,
            "loss": 0.8487343435937709,
            "decision": 1,
            "drift_rate": 0.0,
            "target_domain": "cartoon"
        },
        {
            "t": 25,
            "accuracy": 0.6510416666666666,
            "loss": 0.8906093510714445,
            "decision": 0,
            "drift_rate": 0.0,
            "target_domain": "cartoon"
        },
        {
            "t": 26,
            "accuracy": 0.6510416666666666,
            "loss": 0.8972338925708424,
            "decision": 0,
            "drift_rate": 0.0,
            "target_domain": "cartoon"
        },
        {
            "t": 27,
            "accuracy": 0.6510416666666666,
            "loss": 0.8917100537906993,
            "decision": 0,
            "drift_rate": 0.0,
            "target_domain": "cartoon"
        },
        {
            "t": 28,
            "accuracy": 0.6510416666666666,
            "loss": 0.8343908570029519,
            "decision": 1,
            "drift_rate": 0.0,
            "target_domain": "cartoon"
        },
        {
            "t": 29,
            "accuracy": 0.7057291666666666,
            "loss": 0.8497501774267717,
            "decision": 0,
            "drift_rate": 0.0,
            "target_domain": "cartoon"
        },
        {
            "t": 30,
            "accuracy": 0.7057291666666666,
            "loss": 0.8483552390878851,
            "decision": 0,
            "drift_rate": 0.0,
            "target_domain": "cartoon"
        },
        {
            "t": 31,
            "accuracy": 0.7057291666666666,
            "loss": 0.8538888476111672,
            "decision": 0,
            "drift_rate": 0.0,
            "target_domain": "cartoon"
        },
        {
            "t": 32,
            "accuracy": 0.7057291666666666,
            "loss": 0.8397449227896604,
            "decision": 1,
            "drift_rate": 0.0,
            "target_domain": "cartoon"
        },
        {
            "t": 33,
            "accuracy": 0.6770833333333334,
            "loss": 0.9146020087328824,
            "decision": 0,
            "drift_rate": 0.0,
            "target_domain": "cartoon"
        },
        {
            "t": 34,
            "accuracy": 0.6770833333333334,
            "loss": 0.9134669737382368,
            "decision": 0,
            "drift_rate": 0.0,
            "target_domain": "cartoon"
        },
        {
            "t": 35,
            "accuracy": 0.6770833333333334,
            "loss": 0.9073721387169578,
            "decision": 0,
            "drift_rate": 0.0,
            "target_domain": "cartoon"
        },
        {
            "t": 36,
            "accuracy": 0.6770833333333334,
            "loss": 0.8166189708492972,
            "decision": 1,
            "drift_rate": 0.0,
            "target_domain": "cartoon"
        },
        {
            "t": 37,
            "accuracy": 0.6753472288449606,
            "loss": 0.7811588699167425,
            "decision": 0,
            "drift_rate": 0.0,
            "target_domain": "cartoon"
        },
        {
            "t": 38,
            "accuracy": 0.6753472288449606,
            "loss": 0.7778299234130166,
            "decision": 0,
            "drift_rate": 0.0,
            "target_domain": "cartoon"
        },
        {
            "t": 39,
            "accuracy": 0.6753472288449606,
            "loss": 0.7821201682090759,
            "decision": 0,
            "drift_rate": 0.0,
            "target_domain": "cartoon"
        },
        {
            "t": 40,
            "accuracy": 0.6753472288449606,
            "loss": 0.797710957852277,
            "decision": 1,
            "drift_rate": 0.0,
            "target_domain": "cartoon"
        },
        {
            "t": 41,
            "accuracy": 0.6857638955116272,
            "loss": 0.8026673251932318,
            "decision": 0,
            "drift_rate": 0.0,
            "target_domain": "cartoon"
        },
        {
            "t": 42,
            "accuracy": 0.6857638955116272,
            "loss": 0.8116949309002269,
            "decision": 0,
            "drift_rate": 0.0,
            "target_domain": "cartoon"
        },
        {
            "t": 43,
            "accuracy": 0.6857638955116272,
            "loss": 0.8104582266374067,
            "decision": 0,
            "drift_rate": 0.0,
            "target_domain": "cartoon"
        },
        {
            "t": 44,
            "accuracy": 0.6857638955116272,
            "loss": 0.8469486832618713,
            "decision": 1,
            "drift_rate": 0.0,
            "target_domain": "cartoon"
        },
        {
            "t": 45,
            "accuracy": 0.5355902910232544,
            "loss": 1.5643960454247214,
            "decision": 0,
            "drift_rate": 0.0,
            "target_domain": "cartoon"
        },
        {
            "t": 46,
            "accuracy": 0.5355902910232544,
            "loss": 1.5579300251874058,
            "decision": 0,
            "drift_rate": 0.0,
            "target_domain": "cartoon"
        },
        {
            "t": 47,
            "accuracy": 0.5355902910232544,
            "loss": 1.562124794179743,
            "decision": 0,
            "drift_rate": 0.0,
            "target_domain": "cartoon"
        },
        {
            "t": 48,
            "accuracy": 0.5355902910232544,
            "loss": 0.8474396033720537,
            "decision": 1,
            "drift_rate": 0.0,
            "target_domain": "cartoon"
        },
        {
            "t": 49,
            "accuracy": 0.6371527910232544,
            "loss": 1.1963884396986528,
            "decision": 0,
            "drift_rate": 0.0,
            "target_domain": "cartoon"
        },
        {
            "t": 50,
            "accuracy": 0.5499614278475443,
            "loss": 1.9723217762433565,
            "decision": 0,
            "drift_rate": 0.2,
            "target_domain": "cartoon"
        },
        {
            "t": 51,
            "accuracy": 0.48257212340831757,
            "loss": 2.554670289158821,
            "decision": 0,
            "drift_rate": 0.2,
            "target_domain": "cartoon"
        },
        {
            "t": 52,
            "accuracy": 0.4014204561710358,
            "loss": 1.4786112245760465,
            "decision": 1,
            "drift_rate": 0.2,
            "target_domain": "cartoon"
        },
        {
            "t": 53,
            "accuracy": 0.46596466898918154,
            "loss": 1.5580994305403337,
            "decision": 0,
            "drift_rate": 0.2,
            "target_domain": "cartoon"
        },
        {
            "t": 54,
            "accuracy": 0.4707961330811183,
            "loss": 1.6236183047294617,
            "decision": 0,
            "drift_rate": 0.2,
            "target_domain": "cartoon"
        },
        {
            "t": 55,
            "accuracy": 0.4707961330811183,
            "loss": 1.6430630867297833,
            "decision": 0,
            "drift_rate": 0.0,
            "target_domain": "cartoon"
        },
        {
            "t": 56,
            "accuracy": 0.4707961330811183,
            "loss": 1.3139560245550594,
            "decision": 1,
            "drift_rate": 0.0,
            "target_domain": "cartoon"
        },
        {
            "t": 57,
            "accuracy": 0.4371279776096344,
            "loss": 1.5882886877426734,
            "decision": 0,
            "drift_rate": 0.0,
            "target_domain": "cartoon"
        },
        {
            "t": 58,
            "accuracy": 0.4371279776096344,
            "loss": 1.5929823976296644,
            "decision": 0,
            "drift_rate": 0.0,
            "target_domain": "cartoon"
        },
        {
            "t": 59,
            "accuracy": 0.4371279776096344,
            "loss": 1.5877285737257738,
            "decision": 0,
            "drift_rate": 0.0,
            "target_domain": "cartoon"
        },
        {
            "t": 60,
            "accuracy": 0.4371279776096344,
            "loss": 1.2634418308734894,
            "decision": 1,
            "drift_rate": 0.0,
            "target_domain": "cartoon"
        },
        {
            "t": 61,
            "accuracy": 0.531063993771871,
            "loss": 1.316865549637721,
            "decision": 0,
            "drift_rate": 0.0,
            "target_domain": "cartoon"
        },
        {
            "t": 62,
            "accuracy": 0.531063993771871,
            "loss": 1.3101165569745576,
            "decision": 0,
            "drift_rate": 0.0,
            "target_domain": "cartoon"
        },
        {
            "t": 63,
            "accuracy": 0.531063993771871,
            "loss": 1.3172961611014147,
            "decision": 0,
            "drift_rate": 0.0,
            "target_domain": "cartoon"
        },
        {
            "t": 64,
            "accuracy": 0.531063993771871,
            "loss": 1.207832240141355,
            "decision": 1,
            "drift_rate": 0.0,
            "target_domain": "cartoon"
        },
        {
            "t": 65,
            "accuracy": 0.5909598271052042,
            "loss": 1.1395735236314626,
            "decision": 0,
            "drift_rate": 0.0,
            "target_domain": "cartoon"
        },
        {
            "t": 66,
            "accuracy": 0.5909598271052042,
            "loss": 1.1295929574049437,
            "decision": 0,
            "drift_rate": 0.0,
            "target_domain": "cartoon"
        },
        {
            "t": 67,
            "accuracy": 0.5909598271052042,
            "loss": 1.1325893493799062,
            "decision": 0,
            "drift_rate": 0.0,
            "target_domain": "cartoon"
        },
        {
            "t": 68,
            "accuracy": 0.5909598271052042,
            "loss": 1.2113752399499598,
            "decision": 1,
            "drift_rate": 0.0,
            "target_domain": "cartoon"
        },
        {
            "t": 69,
            "accuracy": 0.5011160771052042,
            "loss": 1.5032031673651476,
            "decision": 0,
            "drift_rate": 0.0,
            "target_domain": "cartoon"
        },
        {
            "t": 70,
            "accuracy": 0.5011160771052042,
            "loss": 1.5282955857423635,
            "decision": 0,
            "drift_rate": 0.0,
            "target_domain": "cartoon"
        },
        {
            "t": 71,
            "accuracy": 0.5011160771052042,
            "loss": 1.5050395864706774,
            "decision": 0,
            "drift_rate": 0.0,
            "target_domain": "cartoon"
        },
        {
            "t": 72,
            "accuracy": 0.5011160771052042,
            "loss": 1.1762345123749514,
            "decision": 1,
            "drift_rate": 0.0,
            "target_domain": "cartoon"
        },
        {
            "t": 73,
            "accuracy": 0.5561755994955698,
            "loss": 1.184783820922558,
            "decision": 0,
            "drift_rate": 0.0,
            "target_domain": "cartoon"
        },
        {
            "t": 74,
            "accuracy": 0.5561755994955698,
            "loss": 1.2044103145599365,
            "decision": 0,
            "drift_rate": 0.0,
            "target_domain": "cartoon"
        },
        {
            "t": 75,
            "accuracy": 0.5561755994955698,
            "loss": 1.1998147781078632,
            "decision": 0,
            "drift_rate": 0.0,
            "target_domain": "cartoon"
        },
        {
            "t": 76,
            "accuracy": 0.5561755994955698,
            "loss": 1.1501432347756166,
            "decision": 1,
            "drift_rate": 0.0,
            "target_domain": "cartoon"
        },
        {
            "t": 77,
            "accuracy": 0.5264136989911398,
            "loss": 1.2520745946810796,
            "decision": 0,
            "drift_rate": 0.0,
            "target_domain": "cartoon"
        },
        {
            "t": 78,
            "accuracy": 0.5264136989911398,
            "loss": 1.244065495637747,
            "decision": 0,
            "drift_rate": 0.0,
            "target_domain": "cartoon"
        },
        {
            "t": 79,
            "accuracy": 0.5264136989911398,
            "loss": 1.250001623080327,
            "decision": 0,
            "drift_rate": 0.0,
            "target_domain": "cartoon"
        },
        {
            "t": 80,
            "accuracy": 0.5264136989911398,
            "loss": 1.111986592411995,
            "decision": 1,
            "drift_rate": 0.0,
            "target_domain": "cartoon"
        },
        {
            "t": 81,
            "accuracy": 0.605282743771871,
            "loss": 1.0874299200681539,
            "decision": 0,
            "drift_rate": 0.0,
            "target_domain": "cartoon"
        },
        {
            "t": 82,
            "accuracy": 0.605282743771871,
            "loss": 1.0858145104004786,
            "decision": 0,
            "drift_rate": 0.0,
            "target_domain": "cartoon"
        },
        {
            "t": 83,
            "accuracy": 0.605282743771871,
            "loss": 1.083439045227491,
            "decision": 0,
            "drift_rate": 0.0,
            "target_domain": "cartoon"
        },
        {
            "t": 84,
            "accuracy": 0.605282743771871,
            "loss": 1.138532240803425,
            "decision": 1,
            "drift_rate": 0.0,
            "target_domain": "cartoon"
        },
        {
            "t": 85,
            "accuracy": 0.5859375,
            "loss": 1.1365063717732062,
            "decision": 0,
            "drift_rate": 0.0,
            "target_domain": "cartoon"
        },
        {
            "t": 86,
            "accuracy": 0.5859375,
            "loss": 1.1398601233959198,
            "decision": 0,
            "drift_rate": 0.0,
            "target_domain": "cartoon"
        },
        {
            "t": 87,
            "accuracy": 0.5859375,
            "loss": 1.1347853655998523,
            "decision": 0,
            "drift_rate": 0.0,
            "target_domain": "cartoon"
        },
        {
            "t": 88,
            "accuracy": 0.5859375,
            "loss": 1.0857754280933967,
            "decision": 1,
            "drift_rate": 0.0,
            "target_domain": "cartoon"
        },
        {
            "t": 89,
            "accuracy": 0.5703125,
            "loss": 1.1638149389853845,
            "decision": 0,
            "drift_rate": 0.0,
            "target_domain": "cartoon"
        },
        {
            "t": 90,
            "accuracy": 0.5703125,
            "loss": 1.1592286412532513,
            "decision": 0,
            "drift_rate": 0.0,
            "target_domain": "cartoon"
        },
        {
            "t": 91,
            "accuracy": 0.5703125,
            "loss": 1.1792747263724987,
            "decision": 0,
            "drift_rate": 0.0,
            "target_domain": "cartoon"
        },
        {
            "t": 92,
            "accuracy": 0.5703125,
            "loss": 1.07000827560058,
            "decision": 1,
            "drift_rate": 0.0,
            "target_domain": "cartoon"
        },
        {
            "t": 93,
            "accuracy": 0.5470610161622366,
            "loss": 1.1872167908228362,
            "decision": 0,
            "drift_rate": 0.0,
            "target_domain": "cartoon"
        },
        {
            "t": 94,
            "accuracy": 0.5470610161622366,
            "loss": 1.1859176204754756,
            "decision": 0,
            "drift_rate": 0.0,
            "target_domain": "cartoon"
        },
        {
            "t": 95,
            "accuracy": 0.5470610161622366,
            "loss": 1.17681206877415,
            "decision": 0,
            "drift_rate": 0.0,
            "target_domain": "cartoon"
        },
        {
            "t": 96,
            "accuracy": 0.5470610161622366,
            "loss": 1.0452238676639705,
            "decision": 1,
            "drift_rate": 0.0,
            "target_domain": "cartoon"
        },
        {
            "t": 97,
            "accuracy": 0.6026785771052042,
            "loss": 1.0068148718430445,
            "decision": 0,
            "drift_rate": 0.0,
            "target_domain": "cartoon"
        },
        {
            "t": 98,
            "accuracy": 0.6026785771052042,
            "loss": 1.001759267770327,
            "decision": 0,
            "drift_rate": 0.0,
            "target_domain": "cartoon"
        },
        {
            "t": 99,
            "accuracy": 0.6026785771052042,
            "loss": 1.0047171734846556,
            "decision": 0,
            "drift_rate": 0.0,
            "target_domain": "cartoon"
        },
        {
            "t": 100,
            "accuracy": 0.6243303503308978,
            "loss": 1.0297649926864185,
            "decision": 1,
            "drift_rate": 0.2,
            "target_domain": "cartoon"
        },
        {
            "t": 101,
            "accuracy": 0.6141517843518939,
            "loss": 1.0931068383730376,
            "decision": 0,
            "drift_rate": 0.2,
            "target_domain": "cartoon"
        },
        {
            "t": 102,
            "accuracy": 0.6141517843518939,
            "loss": 1.0728511283030877,
            "decision": 0,
            "drift_rate": 0.2,
            "target_domain": "cartoon"
        },
        {
            "t": 103,
            "accuracy": 0.6141517843518939,
            "loss": 1.08440235715646,
            "decision": 0,
            "drift_rate": 0.2,
            "target_domain": "cartoon"
        },
        {
            "t": 104,
            "accuracy": 0.6141517843518939,
            "loss": 1.04318196613055,
            "decision": 1,
            "drift_rate": 0.2,
            "target_domain": "cartoon"
        },
        {
            "t": 105,
            "accuracy": 0.47120535373687744,
            "loss": 1.3905075467549837,
            "decision": 0,
            "drift_rate": 0.0,
            "target_domain": "sketch"
        },
        {
            "t": 106,
            "accuracy": 0.47120535373687744,
            "loss": 1.3873274142925556,
            "decision": 0,
            "drift_rate": 0.0,
            "target_domain": "sketch"
        },
        {
            "t": 107,
            "accuracy": 0.47120535373687744,
            "loss": 1.3737788544251368,
            "decision": 0,
            "drift_rate": 0.0,
            "target_domain": "sketch"
        },
        {
            "t": 108,
            "accuracy": 0.47120535373687744,
            "loss": 1.000128767811335,
            "decision": 1,
            "drift_rate": 0.0,
            "target_domain": "sketch"
        },
        {
            "t": 109,
            "accuracy": 0.5442857146263123,
            "loss": 1.3496864254658039,
            "decision": 0,
            "drift_rate": 0.0,
            "target_domain": "sketch"
        },
        {
            "t": 110,
            "accuracy": 0.5442857146263123,
            "loss": 1.3515232572188745,
            "decision": 0,
            "drift_rate": 0.0,
            "target_domain": "sketch"
        },
        {
            "t": 111,
            "accuracy": 0.5442857146263123,
            "loss": 1.3678379975832426,
            "decision": 0,
            "drift_rate": 0.0,
            "target_domain": "sketch"
        },
        {
            "t": 112,
            "accuracy": 0.5442857146263123,
            "loss": 1.015707342670514,
            "decision": 1,
            "drift_rate": 0.0,
            "target_domain": "sketch"
        },
        {
            "t": 113,
            "accuracy": 0.6130357129233224,
            "loss": 1.0678630700478187,
            "decision": 0,
            "drift_rate": 0.0,
            "target_domain": "sketch"
        },
        {
            "t": 114,
            "accuracy": 0.6130357129233224,
            "loss": 1.062090779726322,
            "decision": 0,
            "drift_rate": 0.0,
            "target_domain": "sketch"
        },
        {
            "t": 115,
            "accuracy": 0.6130357129233224,
            "loss": 1.0594595166353078,
            "decision": 0,
            "drift_rate": 0.0,
            "target_domain": "sketch"
        },
        {
            "t": 116,
            "accuracy": 0.6130357129233224,
            "loss": 1.0132256127320802,
            "decision": 1,
            "drift_rate": 0.0,
            "target_domain": "sketch"
        },
        {
            "t": 117,
            "accuracy": 0.6003571408135551,
            "loss": 1.0836591262083788,
            "decision": 0,
            "drift_rate": 0.0,
            "target_domain": "sketch"
        },
        {
            "t": 118,
            "accuracy": 0.6003571408135551,
            "loss": 1.0849189483202422,
            "decision": 0,
            "drift_rate": 0.0,
            "target_domain": "sketch"
        },
        {
            "t": 119,
            "accuracy": 0.6003571408135551,
            "loss": 1.0975891856046824,
            "decision": 0,
            "drift_rate": 0.0,
            "target_domain": "sketch"
        },
        {
            "t": 120,
            "accuracy": 0.6003571408135551,
            "loss": 0.9916290801305037,
            "decision": 1,
            "drift_rate": 0.0,
            "target_domain": "sketch"
        },
        {
            "t": 121,
            "accuracy": 0.6049553581646511,
            "loss": 1.054844631598546,
            "decision": 0,
            "drift_rate": 0.0,
            "target_domain": "sketch"
        },
        {
            "t": 122,
            "accuracy": 0.6049553581646511,
            "loss": 1.0690361307217524,
            "decision": 0,
            "drift_rate": 0.0,
            "target_domain": "sketch"
        },
        {
            "t": 123,
            "accuracy": 0.6049553581646511,
            "loss": 1.0815476431296422,
            "decision": 0,
            "drift_rate": 0.0,
            "target_domain": "sketch"
        },
        {
            "t": 124,
            "accuracy": 0.6049553581646511,
            "loss": 0.9465276644780085,
            "decision": 1,
            "drift_rate": 0.0,
            "target_domain": "sketch"
        },
        {
            "t": 125,
            "accuracy": 0.6020089217594692,
            "loss": 1.1660255193710327,
            "decision": 0,
            "drift_rate": 0.0,
            "target_domain": "sketch"
        },
        {
            "t": 126,
            "accuracy": 0.6020089217594692,
            "loss": 1.1707886755466461,
            "decision": 0,
            "drift_rate": 0.0,
            "target_domain": "sketch"
        },
        {
            "t": 127,
            "accuracy": 0.6020089217594692,
            "loss": 1.1743401564084566,
            "decision": 0,
            "drift_rate": 0.0,
            "target_domain": "sketch"
        },
        {
            "t": 128,
            "accuracy": 0.6020089217594692,
            "loss": 0.9952592035898795,
            "decision": 1,
            "drift_rate": 0.0,
            "target_domain": "sketch"
        },
        {
            "t": 129,
            "accuracy": 0.5332589234624591,
            "loss": 1.809662864758418,
            "decision": 0,
            "drift_rate": 0.0,
            "target_domain": "sketch"
        },
        {
            "t": 130,
            "accuracy": 0.5332589234624591,
            "loss": 1.7764209692294781,
            "decision": 0,
            "drift_rate": 0.0,
            "target_domain": "sketch"
        },
        {
            "t": 131,
            "accuracy": 0.5332589234624591,
            "loss": 1.757957942210711,
            "decision": 0,
            "drift_rate": 0.0,
            "target_domain": "sketch"
        },
        {
            "t": 132,
            "accuracy": 0.5332589234624591,
            "loss": 0.9768101286429626,
            "decision": 1,
            "drift_rate": 0.0,
            "target_domain": "sketch"
        },
        {
            "t": 133,
            "accuracy": 0.6037053550992694,
            "loss": 1.0976031583089094,
            "decision": 0,
            "drift_rate": 0.0,
            "target_domain": "sketch"
        },
        {
            "t": 134,
            "accuracy": 0.6037053550992694,
            "loss": 1.10046363564638,
            "decision": 0,
            "drift_rate": 0.0,
            "target_domain": "sketch"
        },
        {
            "t": 135,
            "accuracy": 0.6037053550992694,
            "loss": 1.090585442689749,
            "decision": 0,
            "drift_rate": 0.0,
            "target_domain": "sketch"
        },
        {
            "t": 136,
            "accuracy": 0.6037053550992694,
            "loss": 0.9425802351190493,
            "decision": 1,
            "drift_rate": 0.0,
            "target_domain": "sketch"
        },
        {
            "t": 137,
            "accuracy": 0.6363392812865121,
            "loss": 1.0190421640872955,
            "decision": 0,
            "drift_rate": 0.0,
            "target_domain": "sketch"
        },
        {
            "t": 138,
            "accuracy": 0.6363392812865121,
            "loss": 1.013580491909614,
            "decision": 0,
            "drift_rate": 0.0,
            "target_domain": "sketch"
        },
        {
            "t": 139,
            "accuracy": 0.6363392812865121,
            "loss": 1.0048574277987847,
            "decision": 0,
            "drift_rate": 0.0,
            "target_domain": "sketch"
        },
        {
            "t": 140,
            "accuracy": 0.6363392812865121,
            "loss": 0.9605094011013324,
            "decision": 1,
            "drift_rate": 0.0,
            "target_domain": "sketch"
        },
        {
            "t": 141,
            "accuracy": 0.6467857105391366,
            "loss": 0.9702087594912603,
            "decision": 0,
            "drift_rate": 0.0,
            "target_domain": "sketch"
        },
        {
            "t": 142,
            "accuracy": 0.6467857105391366,
            "loss": 0.984901664348749,
            "decision": 0,
            "drift_rate": 0.0,
            "target_domain": "sketch"
        },
        {
            "t": 143,
            "accuracy": 0.6467857105391366,
            "loss": 0.9818840691676507,
            "decision": 0,
            "drift_rate": 0.0,
            "target_domain": "sketch"
        },
        {
            "t": 144,
            "accuracy": 0.6467857105391366,
            "loss": 0.9542900805289929,
            "decision": 1,
            "drift_rate": 0.0,
            "target_domain": "sketch"
        },
        {
            "t": 145,
            "accuracy": 0.6126339265278408,
            "loss": 1.0376642575630775,
            "decision": 0,
            "drift_rate": 0.0,
            "target_domain": "sketch"
        },
        {
            "t": 146,
            "accuracy": 0.6126339265278408,
            "loss": 1.0409569969544044,
            "decision": 0,
            "drift_rate": 0.0,
            "target_domain": "sketch"
        },
        {
            "t": 147,
            "accuracy": 0.6126339265278408,
            "loss": 1.0510313327495868,
            "decision": 0,
            "drift_rate": 0.0,
            "target_domain": "sketch"
        },
        {
            "t": 148,
            "accuracy": 0.6126339265278408,
            "loss": 0.9155932366847992,
            "decision": 1,
            "drift_rate": 0.0,
            "target_domain": "sketch"
        },
        {
            "t": 149,
            "accuracy": 0.6194642867360797,
            "loss": 0.982691044990833,
            "decision": 0,
            "drift_rate": 0.0,
            "target_domain": "sketch"
        },
        {
            "t": 150,
            "accuracy": 0.5694424659013748,
            "loss": 1.1136719142237017,
            "decision": 0,
            "drift_rate": 0.2,
            "target_domain": "sketch"
        },
        {
            "t": 151,
            "accuracy": 0.5096450646718343,
            "loss": 1.2605087016079877,
            "decision": 0,
            "drift_rate": 0.2,
            "target_domain": "sketch"
        },
        {
            "t": 152,
            "accuracy": 0.4735220887444236,
            "loss": 1.223135459152135,
            "decision": 1,
            "drift_rate": 0.2,
            "target_domain": "sketch"
        },
        {
            "t": 153,
            "accuracy": 0.4588624835014343,
            "loss": 1.3169478130340577,
            "decision": 0,
            "drift_rate": 0.2,
            "target_domain": "sketch"
        },
        {
            "t": 154,
            "accuracy": 0.4588624835014343,
            "loss": 1.3155835747718811,
            "decision": 0,
            "drift_rate": 0.2,
            "target_domain": "sketch"
        },
        {
            "t": 155,
            "accuracy": 0.4588624835014343,
            "loss": 1.3161193680763246,
            "decision": 0,
            "drift_rate": 0.0,
            "target_domain": "photo"
        },
        {
            "t": 156,
            "accuracy": 0.4588624835014343,
            "loss": 1.1756580084562303,
            "decision": 1,
            "drift_rate": 0.0,
            "target_domain": "photo"
        },
        {
            "t": 157,
            "accuracy": 0.49391101415340716,
            "loss": 1.2167489171028136,
            "decision": 0,
            "drift_rate": 0.0,
            "target_domain": "photo"
        },
        {
            "t": 158,
            "accuracy": 0.49391101415340716,
            "loss": 1.2187182784080506,
            "decision": 0,
            "drift_rate": 0.0,
            "target_domain": "photo"
        },
        {
            "t": 159,
            "accuracy": 0.49391101415340716,
            "loss": 1.216942596435547,
            "decision": 0,
            "drift_rate": 0.0,
            "target_domain": "photo"
        },
        {
            "t": 160,
            "accuracy": 0.49391101415340716,
            "loss": 1.145067160129547,
            "decision": 1,
            "drift_rate": 0.0,
            "target_domain": "photo"
        },
        {
            "t": 161,
            "accuracy": 0.49291319113511306,
            "loss": 1.2143437671661377,
            "decision": 0,
            "drift_rate": 0.0,
            "target_domain": "photo"
        },
        {
            "t": 162,
            "accuracy": 0.49291319113511306,
            "loss": 1.2144578623771667,
            "decision": 0,
            "drift_rate": 0.0,
            "target_domain": "photo"
        },
        {
            "t": 163,
            "accuracy": 0.49291319113511306,
            "loss": 1.2131997108459474,
            "decision": 0,
            "drift_rate": 0.0,
            "target_domain": "photo"
        },
        {
            "t": 164,
            "accuracy": 0.49291319113511306,
            "loss": 1.151305518746376,
            "decision": 1,
            "drift_rate": 0.0,
            "target_domain": "photo"
        },
        {
            "t": 165,
            "accuracy": 0.4914051156777602,
            "loss": 1.26926323056221,
            "decision": 0,
            "drift_rate": 0.0,
            "target_domain": "photo"
        },
        {
            "t": 166,
            "accuracy": 0.4914051156777602,
            "loss": 1.2678387427330018,
            "decision": 0,
            "drift_rate": 0.0,
            "target_domain": "photo"
        },
        {
            "t": 167,
            "accuracy": 0.4914051156777602,
            "loss": 1.2682700490951537,
            "decision": 0,
            "drift_rate": 0.0,
            "target_domain": "photo"
        },
        {
            "t": 168,
            "accuracy": 0.4914051156777602,
            "loss": 1.110557806491852,
            "decision": 1,
            "drift_rate": 0.0,
            "target_domain": "photo"
        },
        {
            "t": 169,
            "accuracy": 0.5697795702860906,
            "loss": 1.035353946685791,
            "decision": 0,
            "drift_rate": 0.0,
            "target_domain": "photo"
        },
        {
            "t": 170,
            "accuracy": 0.5697795702860906,
            "loss": 1.0365702152252196,
            "decision": 0,
            "drift_rate": 0.0,
            "target_domain": "photo"
        },
        {
            "t": 171,
            "accuracy": 0.5697795702860906,
            "loss": 1.032237149477005,
            "decision": 0,
            "drift_rate": 0.0,
            "target_domain": "photo"
        },
        {
            "t": 172,
            "accuracy": 0.5697795702860906,
            "loss": 1.103475380539894,
            "decision": 1,
            "drift_rate": 0.0,
            "target_domain": "photo"
        },
        {
            "t": 173,
            "accuracy": 0.5584633533771222,
            "loss": 1.1028645491600038,
            "decision": 0,
            "drift_rate": 0.0,
            "target_domain": "photo"
        },
        {
            "t": 174,
            "accuracy": 0.5584633533771222,
            "loss": 1.1004910564422608,
            "decision": 0,
            "drift_rate": 0.0,
            "target_domain": "photo"
        },
        {
            "t": 175,
            "accuracy": 0.5584633533771222,
            "loss": 1.1017113947868347,
            "decision": 0,
            "drift_rate": 0.0,
            "target_domain": "photo"
        },
        {
            "t": 176,
            "accuracy": 0.5584633533771222,
            "loss": 1.0877841794490815,
            "decision": 1,
            "drift_rate": 0.0,
            "target_domain": "photo"
        },
        {
            "t": 177,
            "accuracy": 0.5103410757504977,
            "loss": 1.1389431822299958,
            "decision": 0,
            "drift_rate": 0.0,
            "target_domain": "photo"
        },
        {
            "t": 178,
            "accuracy": 0.5103410757504977,
            "loss": 1.1396489012241364,
            "decision": 0,
            "drift_rate": 0.0,
            "target_domain": "photo"
        },
        {
            "t": 179,
            "accuracy": 0.5103410757504977,
            "loss": 1.1398366737365722,
            "decision": 0,
            "drift_rate": 0.0,
            "target_domain": "photo"
        },
        {
            "t": 180,
            "accuracy": 0.5103410757504977,
            "loss": 1.092161865234375,
            "decision": 1,
            "drift_rate": 0.0,
            "target_domain": "photo"
        },
        {
            "t": 181,
            "accuracy": 0.5244580002931448,
            "loss": 1.0975893366336822,
            "decision": 0,
            "drift_rate": 0.0,
            "target_domain": "photo"
        },
        {
            "t": 182,
            "accuracy": 0.5244580002931448,
            "loss": 1.100303075313568,
            "decision": 0,
            "drift_rate": 0.0,
            "target_domain": "photo"
        },
        {
            "t": 183,
            "accuracy": 0.5244580002931448,
            "loss": 1.0990103852748871,
            "decision": 0,
            "drift_rate": 0.0,
            "target_domain": "photo"
        },
        {
            "t": 184,
            "accuracy": 0.5244580002931448,
            "loss": 1.0736062383651732,
            "decision": 1,
            "drift_rate": 0.0,
            "target_domain": "photo"
        },
        {
            "t": 185,
            "accuracy": 0.5593704650035272,
            "loss": 1.0240837085247039,
            "decision": 0,
            "drift_rate": 0.0,
            "target_domain": "photo"
        },
        {
            "t": 186,
            "accuracy": 0.5593704650035272,
            "loss": 1.0243973135948181,
            "decision": 0,
            "drift_rate": 0.0,
            "target_domain": "photo"
        },
        {
            "t": 187,
            "accuracy": 0.5593704650035272,
            "loss": 1.024785041809082,
            "decision": 0,
            "drift_rate": 0.0,
            "target_domain": "photo"
        },
        {
            "t": 188,
            "accuracy": 0.5593704650035272,
            "loss": 1.05392802298069,
            "decision": 1,
            "drift_rate": 0.0,
            "target_domain": "photo"
        },
        {
            "t": 189,
            "accuracy": 0.5458998542565566,
            "loss": 1.0704604589939117,
            "decision": 0,
            "drift_rate": 0.0,
            "target_domain": "photo"
        },
        {
            "t": 190,
            "accuracy": 0.5458998542565566,
            "loss": 1.0720827627182006,
            "decision": 0,
            "drift_rate": 0.0,
            "target_domain": "photo"
        },
        {
            "t": 191,
            "accuracy": 0.5458998542565566,
            "loss": 1.0711651754379272,
            "decision": 0,
            "drift_rate": 0.0,
            "target_domain": "photo"
        },
        {
            "t": 192,
            "accuracy": 0.5458998542565566,
            "loss": 1.053757444024086,
            "decision": 1,
            "drift_rate": 0.0,
            "target_domain": "photo"
        },
        {
            "t": 193,
            "accuracy": 0.5686796995309683,
            "loss": 1.016460095643997,
            "decision": 0,
            "drift_rate": 0.0,
            "target_domain": "photo"
        },
        {
            "t": 194,
            "accuracy": 0.5686796995309683,
            "loss": 1.0159593439102172,
            "decision": 0,
            "drift_rate": 0.0,
            "target_domain": "photo"
        },
        {
            "t": 195,
            "accuracy": 0.5686796995309683,
            "loss": 1.016070419549942,
            "decision": 0,
            "drift_rate": 0.0,
            "target_domain": "photo"
        },
        {
            "t": 196,
            "accuracy": 0.5686796995309683,
            "loss": 1.036729689836502,
            "decision": 1,
            "drift_rate": 0.0,
            "target_domain": "photo"
        },
        {
            "t": 197,
            "accuracy": 0.526011430300199,
            "loss": 1.1186730575561523,
            "decision": 0,
            "drift_rate": 0.0,
            "target_domain": "photo"
        },
        {
            "t": 198,
            "accuracy": 0.526011430300199,
            "loss": 1.1194805228710174,
            "decision": 0,
            "drift_rate": 0.0,
            "target_domain": "photo"
        },
        {
            "t": 199,
            "accuracy": 0.526011430300199,
            "loss": 1.118721890449524,
            "decision": 0,
            "drift_rate": 0.0,
            "target_domain": "photo"
        }
    ]
}